pathgen/__init__.py
pathgen/main.py
pathgen-0.1.0.dist-info/LICENSE
pathgen-0.1.0.dist-info/METADATA
pathgen-0.1.0.dist-info/WHEEL
pathgen-0.1.0.dist-info/entry_points.txt
pathgen-0.1.0.dist-info/top_level.txt
pathgen-0.1.0.dist-info/RECORD
